subtitle_renamer/__init__.py
subtitle_renamer/cli.py
subtitle_renamer/core.py
subtitle_renamer/utils.py
subtitle_renamer-0.1.2.dist-info/LICENSE
subtitle_renamer-0.1.2.dist-info/METADATA
subtitle_renamer-0.1.2.dist-info/WHEEL
subtitle_renamer-0.1.2.dist-info/entry_points.txt
subtitle_renamer-0.1.2.dist-info/RECORD
